cpputils.cpython-38-darwin.so
infostop/__init__.py
infostop/deprecated.py
infostop/metadata.py
infostop/models.py
infostop/postprocess.py
infostop/utils.py
infostop/visualize.py
tests/__init__.py
tests/test_models.py
infostop-0.1.9.dist-info/LICENSE
infostop-0.1.9.dist-info/METADATA
infostop-0.1.9.dist-info/WHEEL
infostop-0.1.9.dist-info/top_level.txt
infostop-0.1.9.dist-info/RECORD
