Metadata-Version: 2.1
Name: infostop
Version: 0.1.9
Summary: Temporospatial clustering in Python. Well suited for mobility data.
Home-page: https://github.com/ulfaslak/infostop
Author: Ulf Aslak, Laura Alessandretti
Author-email: ulfjensen@gmail.com
License: UNKNOWN
Platform: UNKNOWN
Classifier: Programming Language :: Python :: 3
Classifier: License :: OSI Approved :: MIT License
Classifier: Operating System :: OS Independent
Classifier: Topic :: Scientific/Engineering :: Information Analysis
Classifier: Topic :: Scientific/Engineering :: Mathematics
License-File: LICENSE
Requires-Dist: pybind11 (>=2.4)
Requires-Dist: infomap (==1.0.6)
Requires-Dist: folium (>=0.7.0)
Requires-Dist: numpy
Requires-Dist: tqdm
Requires-Dist: scikit-learn
